[{"category": 1, "name": "(C85) [\u5fd8\u3089\u308b\u308b\u624b\u7d19 (\u3073\u3093\u305b\u3093)] \u30a8\u30eb\u30d5\u59c9\u59b9\u306e\u6311\u6226", "source_link": "http://18h.mm-cg.com/doujin_3549.html", "created_at": "2017-11-07T16:50:19.211Z", "cover": "http://hahost2.imgscloud.com/fileshort/13549/13549_001.jpg", "images": ["http://hahost2.imgscloud.com/fileshort/13549/13549_001.jpg", "http://hahost2.imgscloud.com/fileshort/13549/13549_002.jpg", "http://hahost2.imgscloud.com/fileshort/13549/13549_003.jpg", "http://hahost2.imgscloud.com/fileshort/13549/13549_004.jpg", "http://hahost2.imgscloud.com/fileshort/13549/13549_005.jpg", "http://hahost2.imgscloud.com/fileshort/13549/13549_006.jpg", "http://hahost2.imgscloud.com/fileshort/13549/13549_007.jpg", "http://hahost2.imgscloud.com/fileshort/13549/13549_008.jpg", "http://hahost2.imgscloud.com/fileshort/13549/13549_009.jpg", "http://hahost2.imgscloud.com/fileshort/13549/13549_010.jpg", "http://hahost2.imgscloud.com/fileshort/13549/13549_011.jpg", "http://hahost2.imgscloud.com/fileshort/13549/13549_012.jpg", "http://hahost2.imgscloud.com/fileshort/13549/13549_013.jpg", "http://hahost2.imgscloud.com/fileshort/13549/13549_014.jpg", "http://hahost2.imgscloud.com/fileshort/13549/13549_015.jpg", "http://hahost2.imgscloud.com/fileshort/13549/13549_016.jpg", "http://hahost2.imgscloud.com/fileshort/13549/13549_017.jpg", "http://hahost2.imgscloud.com/fileshort/13549/13549_018.jpg", "http://hahost2.imgscloud.com/fileshort/13549/13549_019.jpg", "http://hahost2.imgscloud.com/fileshort/13549/13549_020.jpg", "http://hahost2.imgscloud.com/fileshort/13549/13549_021.jpg", "http://hahost2.imgscloud.com/fileshort/13549/13549_022.jpg", "http://hahost2.imgscloud.com/fileshort/13549/13549_023.jpg", "http://hahost2.imgscloud.com/fileshort/13549/13549_024.jpg", "http://hahost2.imgscloud.com/fileshort/13549/13549_025.jpg", "http://hahost2.imgscloud.com/fileshort/13549/13549_026.jpg", "http://hahost2.imgscloud.com/fileshort/13549/13549_027.jpg", "http://hahost2.imgscloud.com/fileshort/13549/13549_028.jpg"]}, {"category": 1, "name": "(C84) [\u771f\u9762\u76ee\u5c4b (isao)] \u3052\u3093\u3057\u3051\u3093\u306e\u3048\u308d\u307b\u3093 (\u3052\u3093\u3057\u3051\u3093)", "source_link": "http://18h.mm-cg.com/doujin_3548.html", "created_at": "2017-11-07T16:50:18.758Z", "cover": "http://hahost2.imgscloud.com/fileshort/13548/13548_001.jpg", "images": ["http://hahost2.imgscloud.com/fileshort/13548/13548_001.jpg", "http://hahost2.imgscloud.com/fileshort/13548/13548_002.jpg", "http://hahost2.imgscloud.com/fileshort/13548/13548_003.jpg", "http://hahost2.imgscloud.com/fileshort/13548/13548_004.jpg", "http://hahost2.imgscloud.com/fileshort/13548/13548_005.jpg", "http://hahost2.imgscloud.com/fileshort/13548/13548_006.jpg", "http://hahost2.imgscloud.com/fileshort/13548/13548_007.jpg", "http://hahost2.imgscloud.com/fileshort/13548/13548_008.jpg", "http://hahost2.imgscloud.com/fileshort/13548/13548_009.jpg", "http://hahost2.imgscloud.com/fileshort/13548/13548_010.jpg", "http://hahost2.imgscloud.com/fileshort/13548/13548_011.jpg", "http://hahost2.imgscloud.com/fileshort/13548/13548_012.jpg", "http://hahost2.imgscloud.com/fileshort/13548/13548_013.jpg", "http://hahost2.imgscloud.com/fileshort/13548/13548_014.jpg", "http://hahost2.imgscloud.com/fileshort/13548/13548_015.jpg", "http://hahost2.imgscloud.com/fileshort/13548/13548_016.jpg", "http://hahost2.imgscloud.com/fileshort/13548/13548_017.jpg", "http://hahost2.imgscloud.com/fileshort/13548/13548_018.jpg", "http://hahost2.imgscloud.com/fileshort/13548/13548_019.jpg", "http://hahost2.imgscloud.com/fileshort/13548/13548_020.jpg", "http://hahost2.imgscloud.com/fileshort/13548/13548_021.jpg", "http://hahost2.imgscloud.com/fileshort/13548/13548_022.jpg"]}, {"category": 1, "name": "(C83) [\u5922\u8336\u4f1a (\u3080\u3061\u3083)] \u8105\u3055\u308c\u308c\u3044\u304b\u3061\u3083\u3093 (\u30b9\u30de\u30a4\u30eb\u30d7\u30ea\u30ad\u30e5\u30a2!) [\u54cd\u81ed\u5c41\u6c49\u5316\u7ec4]", "source_link": "http://18h.mm-cg.com/doujin_3547.html", "created_at": "2017-11-07T16:50:18.290Z", "cover": "http://hahost2.imgscloud.com/fileshort/13547/13547_001.jpg", "images": ["http://hahost2.imgscloud.com/fileshort/13547/13547_001.jpg", "http://hahost2.imgscloud.com/fileshort/13547/13547_002.jpg", "http://hahost2.imgscloud.com/fileshort/13547/13547_003.jpg", "http://hahost2.imgscloud.com/fileshort/13547/13547_004.jpg", "http://hahost2.imgscloud.com/fileshort/13547/13547_005.jpg", "http://hahost2.imgscloud.com/fileshort/13547/13547_006.jpg", "http://hahost2.imgscloud.com/fileshort/13547/13547_007.jpg", "http://hahost2.imgscloud.com/fileshort/13547/13547_008.jpg", "http://hahost2.imgscloud.com/fileshort/13547/13547_009.jpg", "http://hahost2.imgscloud.com/fileshort/13547/13547_010.jpg", "http://hahost2.imgscloud.com/fileshort/13547/13547_011.jpg", "http://hahost2.imgscloud.com/fileshort/13547/13547_012.jpg", "http://hahost2.imgscloud.com/fileshort/13547/13547_013.jpg", "http://hahost2.imgscloud.com/fileshort/13547/13547_014.jpg", "http://hahost2.imgscloud.com/fileshort/13547/13547_015.jpg", "http://hahost2.imgscloud.com/fileshort/13547/13547_016.jpg", "http://hahost2.imgscloud.com/fileshort/13547/13547_017.jpg", "http://hahost2.imgscloud.com/fileshort/13547/13547_018.jpg", "http://hahost2.imgscloud.com/fileshort/13547/13547_019.jpg", "http://hahost2.imgscloud.com/fileshort/13547/13547_020.jpg", "http://hahost2.imgscloud.com/fileshort/13547/13547_021.jpg", "http://hahost2.imgscloud.com/fileshort/13547/13547_022.jpg", "http://hahost2.imgscloud.com/fileshort/13547/13547_023.jpg", "http://hahost2.imgscloud.com/fileshort/13547/13547_024.jpg", "http://hahost2.imgscloud.com/fileshort/13547/13547_025.jpg", "http://hahost2.imgscloud.com/fileshort/13547/13547_026.jpg", "http://hahost2.imgscloud.com/fileshort/13547/13547_027.jpg", "http://hahost2.imgscloud.com/fileshort/13547/13547_028.jpg", "http://hahost2.imgscloud.com/fileshort/13547/13547_029.jpg", "http://hahost2.imgscloud.com/fileshort/13547/13547_030.jpg"]}, {"category": 1, "name": "(C83) [\u304a\u3068\u306a\u51fa\u7248(\u3072\u3064\u3058\u305f\u304b\u3053)] \u3061\u3061\u304f\u308a\u30aa\u30f3\u30e9\u30a4\u30f3 (\u30bd\u30fc\u30c9\u30a2\u30fc\u30c8\u30fb\u30aa\u30f3\u30e9\u30a4\u30f3) [\u65e0\u6bd2\u6c49\u5316\u7ec4]", "source_link": "http://18h.mm-cg.com/doujin_3546.html", "created_at": "2017-11-07T16:50:17.829Z", "cover": "http://hahost2.imgscloud.com/fileshort/13546/13546_001.jpg", "images": ["http://hahost2.imgscloud.com/fileshort/13546/13546_001.jpg", "http://hahost2.imgscloud.com/fileshort/13546/13546_002.jpg", "http://hahost2.imgscloud.com/fileshort/13546/13546_003.jpg", "http://hahost2.imgscloud.com/fileshort/13546/13546_004.jpg", "http://hahost2.imgscloud.com/fileshort/13546/13546_005.jpg", "http://hahost2.imgscloud.com/fileshort/13546/13546_006.jpg", "http://hahost2.imgscloud.com/fileshort/13546/13546_007.jpg", "http://hahost2.imgscloud.com/fileshort/13546/13546_008.jpg", "http://hahost2.imgscloud.com/fileshort/13546/13546_009.jpg", "http://hahost2.imgscloud.com/fileshort/13546/13546_010.jpg", "http://hahost2.imgscloud.com/fileshort/13546/13546_011.jpg", "http://hahost2.imgscloud.com/fileshort/13546/13546_012.jpg", "http://hahost2.imgscloud.com/fileshort/13546/13546_013.jpg", "http://hahost2.imgscloud.com/fileshort/13546/13546_014.jpg", "http://hahost2.imgscloud.com/fileshort/13546/13546_015.jpg", "http://hahost2.imgscloud.com/fileshort/13546/13546_016.jpg", "http://hahost2.imgscloud.com/fileshort/13546/13546_017.jpg", "http://hahost2.imgscloud.com/fileshort/13546/13546_018.jpg", "http://hahost2.imgscloud.com/fileshort/13546/13546_019.jpg", "http://hahost2.imgscloud.com/fileshort/13546/13546_020.jpg", "http://hahost2.imgscloud.com/fileshort/13546/13546_021.jpg", "http://hahost2.imgscloud.com/fileshort/13546/13546_022.jpg"]}, {"category": 1, "name": "(C82)[\u3042\u3063\u304b\u3093Bi\uff5e(\u67f3\u3072\u308d\u3072\u3053)] NightHawk\u2169\u2169\u2160\u2169(\u50d5\u306f\u53cb\u9054\u304c\u5c11\u306a\u3044)", "source_link": "http://18h.mm-cg.com/doujin_3545.html", "created_at": "2017-11-07T16:50:17.386Z", "cover": "http://hahost2.imgscloud.com/fileshort/13545/13545_001.jpg", "images": ["http://hahost2.imgscloud.com/fileshort/13545/13545_001.jpg", "http://hahost2.imgscloud.com/fileshort/13545/13545_002.jpg", "http://hahost2.imgscloud.com/fileshort/13545/13545_003.jpg", "http://hahost2.imgscloud.com/fileshort/13545/13545_004.jpg", "http://hahost2.imgscloud.com/fileshort/13545/13545_005.jpg", "http://hahost2.imgscloud.com/fileshort/13545/13545_006.jpg", "http://hahost2.imgscloud.com/fileshort/13545/13545_007.jpg", "http://hahost2.imgscloud.com/fileshort/13545/13545_008.jpg", "http://hahost2.imgscloud.com/fileshort/13545/13545_009.jpg", "http://hahost2.imgscloud.com/fileshort/13545/13545_010.jpg", "http://hahost2.imgscloud.com/fileshort/13545/13545_011.jpg", "http://hahost2.imgscloud.com/fileshort/13545/13545_012.jpg", "http://hahost2.imgscloud.com/fileshort/13545/13545_013.jpg", "http://hahost2.imgscloud.com/fileshort/13545/13545_014.jpg", "http://hahost2.imgscloud.com/fileshort/13545/13545_015.jpg", "http://hahost2.imgscloud.com/fileshort/13545/13545_016.jpg", "http://hahost2.imgscloud.com/fileshort/13545/13545_017.jpg", "http://hahost2.imgscloud.com/fileshort/13545/13545_018.jpg", "http://hahost2.imgscloud.com/fileshort/13545/13545_019.jpg", "http://hahost2.imgscloud.com/fileshort/13545/13545_020.jpg", "http://hahost2.imgscloud.com/fileshort/13545/13545_021.jpg", "http://hahost2.imgscloud.com/fileshort/13545/13545_022.jpg", "http://hahost2.imgscloud.com/fileshort/13545/13545_023.jpg", "http://hahost2.imgscloud.com/fileshort/13545/13545_024.jpg", "http://hahost2.imgscloud.com/fileshort/13545/13545_025.jpg", "http://hahost2.imgscloud.com/fileshort/13545/13545_026.jpg", "http://hahost2.imgscloud.com/fileshort/13545/13545_027.jpg", "http://hahost2.imgscloud.com/fileshort/13545/13545_028.jpg", "http://hahost2.imgscloud.com/fileshort/13545/13545_029.jpg", "http://hahost2.imgscloud.com/fileshort/13545/13545_030.jpg"]}, {"category": 1, "name": "(C81) [ROUTE1 (\u5e73\u3064\u304f\u306d)] HIGH COLOR GIRL (\u30a2\u30a4\u30c9\u30eb\u30de\u30b9\u30bf\u30fc) [\u65e0\u6bd2\u6c49\u5316\u7ec4]", "source_link": "http://18h.mm-cg.com/doujin_3544.html", "created_at": "2017-11-07T16:50:16.924Z", "cover": "http://hahost2.imgscloud.com/fileshort/13544/13544_001.jpg", "images": ["http://hahost2.imgscloud.com/fileshort/13544/13544_001.jpg", "http://hahost2.imgscloud.com/fileshort/13544/13544_002.jpg", "http://hahost2.imgscloud.com/fileshort/13544/13544_003.jpg", "http://hahost2.imgscloud.com/fileshort/13544/13544_004.jpg", "http://hahost2.imgscloud.com/fileshort/13544/13544_005.jpg", "http://hahost2.imgscloud.com/fileshort/13544/13544_006.jpg", "http://hahost2.imgscloud.com/fileshort/13544/13544_007.jpg", "http://hahost2.imgscloud.com/fileshort/13544/13544_008.jpg", "http://hahost2.imgscloud.com/fileshort/13544/13544_009.jpg", "http://hahost2.imgscloud.com/fileshort/13544/13544_010.jpg", "http://hahost2.imgscloud.com/fileshort/13544/13544_011.jpg", "http://hahost2.imgscloud.com/fileshort/13544/13544_012.jpg"]}, {"category": 1, "name": "(C81) [BLACK DOG (\u9ed2\u72ac\u7363)] SUBMISSION-R RE MERCURY(\u7f8e\u5c11\u5973\u6226\u58eb\u30bb\u30fc\u30e9\u30fc\u30e0\u30fc\u30f3) [\u4e2d\u56fd\u7ffb\u8a33]", "source_link": "http://18h.mm-cg.com/doujin_3543.html", "created_at": "2017-11-07T16:50:16.470Z", "cover": "http://hahost2.imgscloud.com/fileshort/13543/13543_001.jpg", "images": ["http://hahost2.imgscloud.com/fileshort/13543/13543_001.jpg", "http://hahost2.imgscloud.com/fileshort/13543/13543_002.jpg", "http://hahost2.imgscloud.com/fileshort/13543/13543_003.jpg", "http://hahost2.imgscloud.com/fileshort/13543/13543_004.jpg", "http://hahost2.imgscloud.com/fileshort/13543/13543_005.jpg", "http://hahost2.imgscloud.com/fileshort/13543/13543_006.jpg", "http://hahost2.imgscloud.com/fileshort/13543/13543_007.jpg", "http://hahost2.imgscloud.com/fileshort/13543/13543_008.jpg", "http://hahost2.imgscloud.com/fileshort/13543/13543_009.jpg", "http://hahost2.imgscloud.com/fileshort/13543/13543_010.jpg", "http://hahost2.imgscloud.com/fileshort/13543/13543_011.jpg", "http://hahost2.imgscloud.com/fileshort/13543/13543_012.jpg", "http://hahost2.imgscloud.com/fileshort/13543/13543_013.jpg", "http://hahost2.imgscloud.com/fileshort/13543/13543_014.jpg", "http://hahost2.imgscloud.com/fileshort/13543/13543_015.jpg", "http://hahost2.imgscloud.com/fileshort/13543/13543_016.jpg", "http://hahost2.imgscloud.com/fileshort/13543/13543_017.jpg", "http://hahost2.imgscloud.com/fileshort/13543/13543_018.jpg", "http://hahost2.imgscloud.com/fileshort/13543/13543_019.jpg", "http://hahost2.imgscloud.com/fileshort/13543/13543_020.jpg", "http://hahost2.imgscloud.com/fileshort/13543/13543_021.jpg", "http://hahost2.imgscloud.com/fileshort/13543/13543_022.jpg", "http://hahost2.imgscloud.com/fileshort/13543/13543_023.jpg", "http://hahost2.imgscloud.com/fileshort/13543/13543_024.jpg", "http://hahost2.imgscloud.com/fileshort/13543/13543_025.jpg", "http://hahost2.imgscloud.com/fileshort/13543/13543_026.jpg", "http://hahost2.imgscloud.com/fileshort/13543/13543_027.jpg", "http://hahost2.imgscloud.com/fileshort/13543/13543_028.jpg", "http://hahost2.imgscloud.com/fileshort/13543/13543_029.jpg", "http://hahost2.imgscloud.com/fileshort/13543/13543_030.jpg", "http://hahost2.imgscloud.com/fileshort/13543/13543_031.jpg", "http://hahost2.imgscloud.com/fileshort/13543/13543_032.jpg", "http://hahost2.imgscloud.com/fileshort/13543/13543_033.jpg", "http://hahost2.imgscloud.com/fileshort/13543/13543_034.jpg", "http://hahost2.imgscloud.com/fileshort/13543/13543_035.jpg", "http://hahost2.imgscloud.com/fileshort/13543/13543_036.jpg", "http://hahost2.imgscloud.com/fileshort/13543/13543_037.jpg", "http://hahost2.imgscloud.com/fileshort/13543/13543_038.jpg", "http://hahost2.imgscloud.com/fileshort/13543/13543_039.jpg", "http://hahost2.imgscloud.com/fileshort/13543/13543_040.jpg", "http://hahost2.imgscloud.com/fileshort/13543/13543_041.jpg", "http://hahost2.imgscloud.com/fileshort/13543/13543_042.jpg", "http://hahost2.imgscloud.com/fileshort/13543/13543_043.jpg", "http://hahost2.imgscloud.com/fileshort/13543/13543_044.jpg", "http://hahost2.imgscloud.com/fileshort/13543/13543_045.jpg", "http://hahost2.imgscloud.com/fileshort/13543/13543_046.jpg", "http://hahost2.imgscloud.com/fileshort/13543/13543_047.jpg", "http://hahost2.imgscloud.com/fileshort/13543/13543_048.jpg", "http://hahost2.imgscloud.com/fileshort/13543/13543_049.jpg", "http://hahost2.imgscloud.com/fileshort/13543/13543_050.jpg", "http://hahost2.imgscloud.com/fileshort/13543/13543_051.jpg", "http://hahost2.imgscloud.com/fileshort/13543/13543_052.jpg", "http://hahost2.imgscloud.com/fileshort/13543/13543_053.jpg", "http://hahost2.imgscloud.com/fileshort/13543/13543_054.jpg", "http://hahost2.imgscloud.com/fileshort/13543/13543_055.jpg"]}, {"category": 1, "name": "(C78) [Private Garden (\u9db4\u5d0e\u8cb4\u5927)] retrieve #10 (\u30c8\u30c8\u30ea\u306e\u30a2\u30c8\u30ea\u30a8 \uff5e\u30a2\u30fc\u30e9\u30f3\u30c9\u306e\u932c\u91d1\u8853\u58eb2\uff5e)[\u4f50\u6a4b\u7686\u4eba\u500b\u4eba\u6f22\u5316]", "source_link": "http://18h.mm-cg.com/doujin_3542.html", "created_at": "2017-11-07T16:50:16.013Z", "cover": "http://hahost2.imgscloud.com/fileshort/13542/13542_001.jpg", "images": ["http://hahost2.imgscloud.com/fileshort/13542/13542_001.jpg", "http://hahost2.imgscloud.com/fileshort/13542/13542_002.jpg", "http://hahost2.imgscloud.com/fileshort/13542/13542_003.jpg", "http://hahost2.imgscloud.com/fileshort/13542/13542_004.jpg", "http://hahost2.imgscloud.com/fileshort/13542/13542_005.jpg", "http://hahost2.imgscloud.com/fileshort/13542/13542_006.jpg", "http://hahost2.imgscloud.com/fileshort/13542/13542_007.jpg", "http://hahost2.imgscloud.com/fileshort/13542/13542_008.jpg", "http://hahost2.imgscloud.com/fileshort/13542/13542_009.jpg", "http://hahost2.imgscloud.com/fileshort/13542/13542_010.jpg", "http://hahost2.imgscloud.com/fileshort/13542/13542_011.jpg", "http://hahost2.imgscloud.com/fileshort/13542/13542_012.jpg", "http://hahost2.imgscloud.com/fileshort/13542/13542_013.jpg", "http://hahost2.imgscloud.com/fileshort/13542/13542_014.jpg", "http://hahost2.imgscloud.com/fileshort/13542/13542_015.jpg", "http://hahost2.imgscloud.com/fileshort/13542/13542_016.jpg"]}, {"category": 1, "name": "(C78) (\u540c\u4eba\u8a8c) [\u3042\u3063\u304b\u3093Bi~ (\u67f3\u3072\u308d\u3072\u3053)] Azz-Hole (\u3051\u3044\u304a\u3093\uff01)", "source_link": "http://18h.mm-cg.com/doujin_3541.html", "created_at": "2017-11-07T16:50:15.379Z", "cover": "http://hahost2.imgscloud.com/fileshort/13541/13541_001.jpg", "images": ["http://hahost2.imgscloud.com/fileshort/13541/13541_001.jpg", "http://hahost2.imgscloud.com/fileshort/13541/13541_002.jpg", "http://hahost2.imgscloud.com/fileshort/13541/13541_003.jpg", "http://hahost2.imgscloud.com/fileshort/13541/13541_004.jpg", "http://hahost2.imgscloud.com/fileshort/13541/13541_005.jpg", "http://hahost2.imgscloud.com/fileshort/13541/13541_006.jpg", "http://hahost2.imgscloud.com/fileshort/13541/13541_007.jpg", "http://hahost2.imgscloud.com/fileshort/13541/13541_008.jpg", "http://hahost2.imgscloud.com/fileshort/13541/13541_009.jpg", "http://hahost2.imgscloud.com/fileshort/13541/13541_010.jpg", "http://hahost2.imgscloud.com/fileshort/13541/13541_011.jpg", "http://hahost2.imgscloud.com/fileshort/13541/13541_012.jpg", "http://hahost2.imgscloud.com/fileshort/13541/13541_013.jpg", "http://hahost2.imgscloud.com/fileshort/13541/13541_014.jpg", "http://hahost2.imgscloud.com/fileshort/13541/13541_015.jpg", "http://hahost2.imgscloud.com/fileshort/13541/13541_016.jpg", "http://hahost2.imgscloud.com/fileshort/13541/13541_017.jpg", "http://hahost2.imgscloud.com/fileshort/13541/13541_018.jpg", "http://hahost2.imgscloud.com/fileshort/13541/13541_019.jpg", "http://hahost2.imgscloud.com/fileshort/13541/13541_020.jpg", "http://hahost2.imgscloud.com/fileshort/13541/13541_021.jpg", "http://hahost2.imgscloud.com/fileshort/13541/13541_022.jpg", "http://hahost2.imgscloud.com/fileshort/13541/13541_023.jpg", "http://hahost2.imgscloud.com/fileshort/13541/13541_024.jpg", "http://hahost2.imgscloud.com/fileshort/13541/13541_025.jpg", "http://hahost2.imgscloud.com/fileshort/13541/13541_026.jpg"]}, {"category": 1, "name": "(C77)(\u540c\u4eba\u8a8c)[\u3080\u3046\u3093\u308b\u3046\u3089\u3042(\u6708\u91ce\u5b9a\u898f)]\u306f\u308b\u304b18(\u30a2\u30de\u30ac\u30df) [\u7121\u4fee\u6b63]", "source_link": "http://18h.mm-cg.com/doujin_3540.html", "created_at": "2017-11-07T16:50:14.941Z", "cover": "http://hahost2.imgscloud.com/fileshort/13540/13540_001.jpg", "images": ["http://hahost2.imgscloud.com/fileshort/13540/13540_001.jpg", "http://hahost2.imgscloud.com/fileshort/13540/13540_002.jpg", "http://hahost2.imgscloud.com/fileshort/13540/13540_003.jpg", "http://hahost2.imgscloud.com/fileshort/13540/13540_004.jpg", "http://hahost2.imgscloud.com/fileshort/13540/13540_005.jpg", "http://hahost2.imgscloud.com/fileshort/13540/13540_006.jpg", "http://hahost2.imgscloud.com/fileshort/13540/13540_007.jpg", "http://hahost2.imgscloud.com/fileshort/13540/13540_008.jpg", "http://hahost2.imgscloud.com/fileshort/13540/13540_009.jpg", "http://hahost2.imgscloud.com/fileshort/13540/13540_010.jpg", "http://hahost2.imgscloud.com/fileshort/13540/13540_011.jpg", "http://hahost2.imgscloud.com/fileshort/13540/13540_012.jpg", "http://hahost2.imgscloud.com/fileshort/13540/13540_013.jpg", "http://hahost2.imgscloud.com/fileshort/13540/13540_014.jpg", "http://hahost2.imgscloud.com/fileshort/13540/13540_015.jpg", "http://hahost2.imgscloud.com/fileshort/13540/13540_016.jpg", "http://hahost2.imgscloud.com/fileshort/13540/13540_017.jpg", "http://hahost2.imgscloud.com/fileshort/13540/13540_018.jpg", "http://hahost2.imgscloud.com/fileshort/13540/13540_019.jpg", "http://hahost2.imgscloud.com/fileshort/13540/13540_020.jpg", "http://hahost2.imgscloud.com/fileshort/13540/13540_021.jpg", "http://hahost2.imgscloud.com/fileshort/13540/13540_022.jpg", "http://hahost2.imgscloud.com/fileshort/13540/13540_023.jpg", "http://hahost2.imgscloud.com/fileshort/13540/13540_024.jpg", "http://hahost2.imgscloud.com/fileshort/13540/13540_025.jpg", "http://hahost2.imgscloud.com/fileshort/13540/13540_026.jpg"]}]