[{"category": 1, "name": "\u3010CE\u5bb6\u65cf\u793e\u3011(COMIC1\u26068) [\u7d14\u9280\u661f (\u305f\u304b\u3057\u306a\u6d45\u5983)] sugarcoatcafe (\u3054\u6ce8\u6587\u306f\u3046\u3055\u304e\u3067\u3059\u304b)", "source_link": "http://18h.mm-cg.com/doujin_1477.html", "created_at": "2017-11-07T16:28:45.561Z", "cover": "http://hahost2.imgscloud.com/fileshort/11477/11477_001.jpg", "images": ["http://hahost2.imgscloud.com/fileshort/11477/11477_001.jpg", "http://hahost2.imgscloud.com/fileshort/11477/11477_002.jpg", "http://hahost2.imgscloud.com/fileshort/11477/11477_003.jpg", "http://hahost2.imgscloud.com/fileshort/11477/11477_004.jpg", "http://hahost2.imgscloud.com/fileshort/11477/11477_005.jpg", "http://hahost2.imgscloud.com/fileshort/11477/11477_006.jpg", "http://hahost2.imgscloud.com/fileshort/11477/11477_007.jpg", "http://hahost2.imgscloud.com/fileshort/11477/11477_008.jpg", "http://hahost2.imgscloud.com/fileshort/11477/11477_009.jpg", "http://hahost2.imgscloud.com/fileshort/11477/11477_010.jpg", "http://hahost2.imgscloud.com/fileshort/11477/11477_011.jpg", "http://hahost2.imgscloud.com/fileshort/11477/11477_012.jpg", "http://hahost2.imgscloud.com/fileshort/11477/11477_013.jpg", "http://hahost2.imgscloud.com/fileshort/11477/11477_014.jpg", "http://hahost2.imgscloud.com/fileshort/11477/11477_015.jpg", "http://hahost2.imgscloud.com/fileshort/11477/11477_016.jpg", "http://hahost2.imgscloud.com/fileshort/11477/11477_017.jpg", "http://hahost2.imgscloud.com/fileshort/11477/11477_018.jpg", "http://hahost2.imgscloud.com/fileshort/11477/11477_019.jpg"]}, {"category": 1, "name": "\u3010CE\u5bb6\u65cf\u793e\u3011(COMIC1\u26068) [SEM;COLON & moco chouchou (\u871c\u30ad\u30f3\u30b0, \u3072\u3055\u307e\u304f\u307e\u3053)] idOLiVE -Blue Lemon Lagoon-", "source_link": "http://18h.mm-cg.com/doujin_1476.html", "created_at": "2017-11-07T16:28:45.119Z", "cover": "http://hahost2.imgscloud.com/fileshort/11476/11476_001.jpg", "images": ["http://hahost2.imgscloud.com/fileshort/11476/11476_001.jpg", "http://hahost2.imgscloud.com/fileshort/11476/11476_002.jpg", "http://hahost2.imgscloud.com/fileshort/11476/11476_003.jpg", "http://hahost2.imgscloud.com/fileshort/11476/11476_004.jpg", "http://hahost2.imgscloud.com/fileshort/11476/11476_005.jpg", "http://hahost2.imgscloud.com/fileshort/11476/11476_006.jpg", "http://hahost2.imgscloud.com/fileshort/11476/11476_007.jpg", "http://hahost2.imgscloud.com/fileshort/11476/11476_008.jpg", "http://hahost2.imgscloud.com/fileshort/11476/11476_009.jpg", "http://hahost2.imgscloud.com/fileshort/11476/11476_010.jpg", "http://hahost2.imgscloud.com/fileshort/11476/11476_011.jpg", "http://hahost2.imgscloud.com/fileshort/11476/11476_012.jpg", "http://hahost2.imgscloud.com/fileshort/11476/11476_013.jpg", "http://hahost2.imgscloud.com/fileshort/11476/11476_014.jpg", "http://hahost2.imgscloud.com/fileshort/11476/11476_015.jpg", "http://hahost2.imgscloud.com/fileshort/11476/11476_016.jpg", "http://hahost2.imgscloud.com/fileshort/11476/11476_017.jpg", "http://hahost2.imgscloud.com/fileshort/11476/11476_018.jpg", "http://hahost2.imgscloud.com/fileshort/11476/11476_019.jpg", "http://hahost2.imgscloud.com/fileshort/11476/11476_020.jpg", "http://hahost2.imgscloud.com/fileshort/11476/11476_021.jpg"]}, {"category": 1, "name": "[\u841d\u8389\u63a7\u4e2a\u4eba\u6c49\u5316](COMIC1\u26068) [\u8c46\u8535 (\u307e\u3081\u305e\u3046)] \u3044\u304a\u308a\u3063\u304f\u3059 \u3042\u306a\u306b\u30fc (\u30a2\u30a4\u30c9\u30eb\u30de\u30b9\u30bf\u30fc)", "source_link": "http://18h.mm-cg.com/doujin_1475.html", "created_at": "2017-11-07T16:28:44.665Z", "cover": "http://hahost2.imgscloud.com/fileshort/11475/11475_001.jpg", "images": ["http://hahost2.imgscloud.com/fileshort/11475/11475_001.jpg", "http://hahost2.imgscloud.com/fileshort/11475/11475_002.jpg", "http://hahost2.imgscloud.com/fileshort/11475/11475_003.jpg", "http://hahost2.imgscloud.com/fileshort/11475/11475_004.jpg", "http://hahost2.imgscloud.com/fileshort/11475/11475_005.jpg", "http://hahost2.imgscloud.com/fileshort/11475/11475_006.jpg", "http://hahost2.imgscloud.com/fileshort/11475/11475_007.jpg", "http://hahost2.imgscloud.com/fileshort/11475/11475_008.jpg", "http://hahost2.imgscloud.com/fileshort/11475/11475_009.jpg", "http://hahost2.imgscloud.com/fileshort/11475/11475_010.jpg", "http://hahost2.imgscloud.com/fileshort/11475/11475_011.jpg", "http://hahost2.imgscloud.com/fileshort/11475/11475_012.jpg", "http://hahost2.imgscloud.com/fileshort/11475/11475_013.jpg", "http://hahost2.imgscloud.com/fileshort/11475/11475_014.jpg", "http://hahost2.imgscloud.com/fileshort/11475/11475_015.jpg", "http://hahost2.imgscloud.com/fileshort/11475/11475_016.jpg", "http://hahost2.imgscloud.com/fileshort/11475/11475_017.jpg", "http://hahost2.imgscloud.com/fileshort/11475/11475_018.jpg"]}, {"category": 1, "name": "[\u841d\u8389\u63a7\u4e2a\u4eba\u6c49\u5316](C83) [\u8c46\u8535 (\u307e\u3081\u305e\u3046)] \u30a4\u30aa\u30ea\u30c3\u30af\u30b9 (\u30a2\u30a4\u30c9\u30eb\u30de\u30b9\u30bf\u30fc)", "source_link": "http://18h.mm-cg.com/doujin_1474.html", "created_at": "2017-11-07T16:28:44.214Z", "cover": "http://hahost2.imgscloud.com/fileshort/11474/11474_001.jpg", "images": ["http://hahost2.imgscloud.com/fileshort/11474/11474_001.jpg", "http://hahost2.imgscloud.com/fileshort/11474/11474_002.jpg", "http://hahost2.imgscloud.com/fileshort/11474/11474_003.jpg", "http://hahost2.imgscloud.com/fileshort/11474/11474_004.jpg", "http://hahost2.imgscloud.com/fileshort/11474/11474_005.jpg", "http://hahost2.imgscloud.com/fileshort/11474/11474_006.jpg", "http://hahost2.imgscloud.com/fileshort/11474/11474_007.jpg", "http://hahost2.imgscloud.com/fileshort/11474/11474_008.jpg", "http://hahost2.imgscloud.com/fileshort/11474/11474_009.jpg", "http://hahost2.imgscloud.com/fileshort/11474/11474_010.jpg", "http://hahost2.imgscloud.com/fileshort/11474/11474_011.jpg", "http://hahost2.imgscloud.com/fileshort/11474/11474_012.jpg", "http://hahost2.imgscloud.com/fileshort/11474/11474_013.jpg", "http://hahost2.imgscloud.com/fileshort/11474/11474_014.jpg", "http://hahost2.imgscloud.com/fileshort/11474/11474_015.jpg", "http://hahost2.imgscloud.com/fileshort/11474/11474_016.jpg", "http://hahost2.imgscloud.com/fileshort/11474/11474_017.jpg", "http://hahost2.imgscloud.com/fileshort/11474/11474_018.jpg"]}, {"category": 1, "name": "[\u8138\u80bf\u6c49\u5316\u7ec4]COMIC\u2606\uff18 \u3054\u304f\u3046\u3059\u52a0\u7b46\u7248\u3000Takamatic After (\u9b54\u6cd5\u5c11\u5973\u30ea\u30ea\u30ab\u30eb\u306a\u306e\u306f)", "source_link": "http://18h.mm-cg.com/doujin_1473.html", "created_at": "2017-11-07T16:28:43.656Z", "cover": "http://hahost2.imgscloud.com/fileshort/11473/11473_001.jpg", "images": ["http://hahost2.imgscloud.com/fileshort/11473/11473_001.jpg", "http://hahost2.imgscloud.com/fileshort/11473/11473_002.jpg", "http://hahost2.imgscloud.com/fileshort/11473/11473_003.jpg", "http://hahost2.imgscloud.com/fileshort/11473/11473_004.jpg", "http://hahost2.imgscloud.com/fileshort/11473/11473_005.jpg", "http://hahost2.imgscloud.com/fileshort/11473/11473_006.jpg", "http://hahost2.imgscloud.com/fileshort/11473/11473_007.jpg", "http://hahost2.imgscloud.com/fileshort/11473/11473_008.jpg", "http://hahost2.imgscloud.com/fileshort/11473/11473_009.jpg", "http://hahost2.imgscloud.com/fileshort/11473/11473_010.jpg", "http://hahost2.imgscloud.com/fileshort/11473/11473_011.jpg", "http://hahost2.imgscloud.com/fileshort/11473/11473_012.jpg", "http://hahost2.imgscloud.com/fileshort/11473/11473_013.jpg", "http://hahost2.imgscloud.com/fileshort/11473/11473_014.jpg"]}, {"category": 1, "name": "[\u8138\u80bf\u6c49\u5316\u7ec4][\u6df1\u6d77\u98db\u884c (\u6c96\u91ce\u7409\u4eba)] sweet prickle (\u30cb\u30bb\u30b3\u30a4) [DL\u7248]", "source_link": "http://18h.mm-cg.com/doujin_1472.html", "created_at": "2017-11-07T16:28:43.186Z", "cover": "http://hahost2.imgscloud.com/fileshort/11472/11472_001.jpg", "images": ["http://hahost2.imgscloud.com/fileshort/11472/11472_001.jpg", "http://hahost2.imgscloud.com/fileshort/11472/11472_002.jpg", "http://hahost2.imgscloud.com/fileshort/11472/11472_003.jpg", "http://hahost2.imgscloud.com/fileshort/11472/11472_004.jpg", "http://hahost2.imgscloud.com/fileshort/11472/11472_005.jpg", "http://hahost2.imgscloud.com/fileshort/11472/11472_006.jpg", "http://hahost2.imgscloud.com/fileshort/11472/11472_007.jpg", "http://hahost2.imgscloud.com/fileshort/11472/11472_008.jpg", "http://hahost2.imgscloud.com/fileshort/11472/11472_009.jpg", "http://hahost2.imgscloud.com/fileshort/11472/11472_010.jpg", "http://hahost2.imgscloud.com/fileshort/11472/11472_011.jpg", "http://hahost2.imgscloud.com/fileshort/11472/11472_012.jpg", "http://hahost2.imgscloud.com/fileshort/11472/11472_013.jpg", "http://hahost2.imgscloud.com/fileshort/11472/11472_014.jpg", "http://hahost2.imgscloud.com/fileshort/11472/11472_015.jpg", "http://hahost2.imgscloud.com/fileshort/11472/11472_016.jpg", "http://hahost2.imgscloud.com/fileshort/11472/11472_017.jpg", "http://hahost2.imgscloud.com/fileshort/11472/11472_018.jpg", "http://hahost2.imgscloud.com/fileshort/11472/11472_019.jpg", "http://hahost2.imgscloud.com/fileshort/11472/11472_020.jpg", "http://hahost2.imgscloud.com/fileshort/11472/11472_021.jpg", "http://hahost2.imgscloud.com/fileshort/11472/11472_022.jpg", "http://hahost2.imgscloud.com/fileshort/11472/11472_023.jpg", "http://hahost2.imgscloud.com/fileshort/11472/11472_024.jpg", "http://hahost2.imgscloud.com/fileshort/11472/11472_025.jpg", "http://hahost2.imgscloud.com/fileshort/11472/11472_026.jpg", "http://hahost2.imgscloud.com/fileshort/11472/11472_027.jpg", "http://hahost2.imgscloud.com/fileshort/11472/11472_028.jpg", "http://hahost2.imgscloud.com/fileshort/11472/11472_029.jpg", "http://hahost2.imgscloud.com/fileshort/11472/11472_030.jpg"]}, {"category": 1, "name": "[\u8138\u80bf\u6c49\u5316\u7ec4][\u5fa1\u7953\u7bb1 (\u5fa1\u672d)] \u53f8\u4ee4\u5b98\u306e\u304a\u624b\u4f1d\u3044 (\u8266\u968a\u3053\u308c\u304f\u3057\u3087\u3093 -\u8266\u3053\u308c-) [DL\u7248]", "source_link": "http://18h.mm-cg.com/doujin_1471.html", "created_at": "2017-11-07T16:28:42.576Z", "cover": "http://hahost2.imgscloud.com/fileshort/11471/11471_001.jpg", "images": ["http://hahost2.imgscloud.com/fileshort/11471/11471_001.jpg", "http://hahost2.imgscloud.com/fileshort/11471/11471_002.jpg", "http://hahost2.imgscloud.com/fileshort/11471/11471_003.jpg", "http://hahost2.imgscloud.com/fileshort/11471/11471_004.jpg", "http://hahost2.imgscloud.com/fileshort/11471/11471_005.jpg", "http://hahost2.imgscloud.com/fileshort/11471/11471_006.jpg", "http://hahost2.imgscloud.com/fileshort/11471/11471_007.jpg", "http://hahost2.imgscloud.com/fileshort/11471/11471_008.jpg", "http://hahost2.imgscloud.com/fileshort/11471/11471_009.jpg", "http://hahost2.imgscloud.com/fileshort/11471/11471_010.jpg", "http://hahost2.imgscloud.com/fileshort/11471/11471_011.jpg", "http://hahost2.imgscloud.com/fileshort/11471/11471_012.jpg", "http://hahost2.imgscloud.com/fileshort/11471/11471_013.jpg", "http://hahost2.imgscloud.com/fileshort/11471/11471_014.jpg", "http://hahost2.imgscloud.com/fileshort/11471/11471_015.jpg", "http://hahost2.imgscloud.com/fileshort/11471/11471_016.jpg", "http://hahost2.imgscloud.com/fileshort/11471/11471_017.jpg", "http://hahost2.imgscloud.com/fileshort/11471/11471_018.jpg", "http://hahost2.imgscloud.com/fileshort/11471/11471_019.jpg", "http://hahost2.imgscloud.com/fileshort/11471/11471_020.jpg", "http://hahost2.imgscloud.com/fileshort/11471/11471_021.jpg", "http://hahost2.imgscloud.com/fileshort/11471/11471_022.jpg", "http://hahost2.imgscloud.com/fileshort/11471/11471_023.jpg", "http://hahost2.imgscloud.com/fileshort/11471/11471_024.jpg", "http://hahost2.imgscloud.com/fileshort/11471/11471_025.jpg", "http://hahost2.imgscloud.com/fileshort/11471/11471_026.jpg", "http://hahost2.imgscloud.com/fileshort/11471/11471_027.jpg", "http://hahost2.imgscloud.com/fileshort/11471/11471_028.jpg", "http://hahost2.imgscloud.com/fileshort/11471/11471_029.jpg"]}, {"category": 1, "name": "[\u8138\u80bf\u6c49\u5316\u7ec4][\u8840\u8272\u871c\u67d1 (\u5eb5\u30ba, ume)] UNPLUGGED (\u3059\u30fc\u3071\u30fc\u305d\u306b\u5b50) [DL\u7248]", "source_link": "http://18h.mm-cg.com/doujin_1470.html", "created_at": "2017-11-07T16:28:42.020Z", "cover": "http://hahost2.imgscloud.com/fileshort/11470/11470_001.jpg", "images": ["http://hahost2.imgscloud.com/fileshort/11470/11470_001.jpg", "http://hahost2.imgscloud.com/fileshort/11470/11470_002.jpg", "http://hahost2.imgscloud.com/fileshort/11470/11470_003.jpg", "http://hahost2.imgscloud.com/fileshort/11470/11470_004.jpg", "http://hahost2.imgscloud.com/fileshort/11470/11470_005.jpg", "http://hahost2.imgscloud.com/fileshort/11470/11470_006.jpg", "http://hahost2.imgscloud.com/fileshort/11470/11470_007.jpg", "http://hahost2.imgscloud.com/fileshort/11470/11470_008.jpg", "http://hahost2.imgscloud.com/fileshort/11470/11470_009.jpg", "http://hahost2.imgscloud.com/fileshort/11470/11470_010.jpg", "http://hahost2.imgscloud.com/fileshort/11470/11470_011.jpg", "http://hahost2.imgscloud.com/fileshort/11470/11470_012.jpg", "http://hahost2.imgscloud.com/fileshort/11470/11470_013.jpg", "http://hahost2.imgscloud.com/fileshort/11470/11470_014.jpg", "http://hahost2.imgscloud.com/fileshort/11470/11470_015.jpg", "http://hahost2.imgscloud.com/fileshort/11470/11470_016.jpg", "http://hahost2.imgscloud.com/fileshort/11470/11470_017.jpg", "http://hahost2.imgscloud.com/fileshort/11470/11470_018.jpg"]}, {"category": 1, "name": "[\u590f\u5eb5] \u8655\u5973\u901a\u59e6\u8a18\u5be6_\u51e6\u5973\u30cd\u30c8\u30ea\u30a2 [\u9ad8\u756b\u8cea]", "source_link": "http://18h.mm-cg.com/18H_5540.html", "created_at": "2017-11-07T16:28:41.584Z", "cover": "http://hahost2.imgscloud.com/file/8218/8218_001.jpg", "images": ["http://hahost2.imgscloud.com/file/8218/8218_001.jpg", "http://hahost2.imgscloud.com/file/8218/8218_002.jpg", "http://hahost2.imgscloud.com/file/8218/8218_003.jpg", "http://hahost2.imgscloud.com/file/8218/8218_004.jpg", "http://hahost2.imgscloud.com/file/8218/8218_005.jpg", "http://hahost2.imgscloud.com/file/8218/8218_006.jpg", "http://hahost2.imgscloud.com/file/8218/8218_007.jpg", "http://hahost2.imgscloud.com/file/8218/8218_008.jpg", "http://hahost2.imgscloud.com/file/8218/8218_009.jpg", "http://hahost2.imgscloud.com/file/8218/8218_010.jpg", "http://hahost2.imgscloud.com/file/8218/8218_011.jpg", "http://hahost2.imgscloud.com/file/8218/8218_012.jpg", "http://hahost2.imgscloud.com/file/8218/8218_013.jpg", "http://hahost2.imgscloud.com/file/8218/8218_014.jpg", "http://hahost2.imgscloud.com/file/8218/8218_015.jpg", "http://hahost2.imgscloud.com/file/8218/8218_016.jpg", "http://hahost2.imgscloud.com/file/8218/8218_017.jpg", "http://hahost2.imgscloud.com/file/8218/8218_018.jpg", "http://hahost2.imgscloud.com/file/8218/8218_019.jpg", "http://hahost2.imgscloud.com/file/8218/8218_020.jpg", "http://hahost2.imgscloud.com/file/8218/8218_021.jpg", "http://hahost2.imgscloud.com/file/8218/8218_022.jpg", "http://hahost2.imgscloud.com/file/8218/8218_023.jpg", "http://hahost2.imgscloud.com/file/8218/8218_024.jpg", "http://hahost2.imgscloud.com/file/8218/8218_025.jpg", "http://hahost2.imgscloud.com/file/8218/8218_026.jpg", "http://hahost2.imgscloud.com/file/8218/8218_027.jpg", "http://hahost2.imgscloud.com/file/8218/8218_028.jpg", "http://hahost2.imgscloud.com/file/8218/8218_029.jpg", "http://hahost2.imgscloud.com/file/8218/8218_030.jpg", "http://hahost2.imgscloud.com/file/8218/8218_031.jpg", "http://hahost2.imgscloud.com/file/8218/8218_032.jpg", "http://hahost2.imgscloud.com/file/8218/8218_033.jpg", "http://hahost2.imgscloud.com/file/8218/8218_034.jpg", "http://hahost2.imgscloud.com/file/8218/8218_035.jpg", "http://hahost2.imgscloud.com/file/8218/8218_036.jpg", "http://hahost2.imgscloud.com/file/8218/8218_037.jpg", "http://hahost2.imgscloud.com/file/8218/8218_038.jpg", "http://hahost2.imgscloud.com/file/8218/8218_039.jpg", "http://hahost2.imgscloud.com/file/8218/8218_040.jpg", "http://hahost2.imgscloud.com/file/8218/8218_041.jpg", "http://hahost2.imgscloud.com/file/8218/8218_042.jpg", "http://hahost2.imgscloud.com/file/8218/8218_043.jpg", "http://hahost2.imgscloud.com/file/8218/8218_044.jpg", "http://hahost2.imgscloud.com/file/8218/8218_045.jpg", "http://hahost2.imgscloud.com/file/8218/8218_046.jpg", "http://hahost2.imgscloud.com/file/8218/8218_047.jpg", "http://hahost2.imgscloud.com/file/8218/8218_048.jpg", "http://hahost2.imgscloud.com/file/8218/8218_049.jpg", "http://hahost2.imgscloud.com/file/8218/8218_050.jpg", "http://hahost2.imgscloud.com/file/8218/8218_051.jpg", "http://hahost2.imgscloud.com/file/8218/8218_052.jpg", "http://hahost2.imgscloud.com/file/8218/8218_053.jpg", "http://hahost2.imgscloud.com/file/8218/8218_054.jpg", "http://hahost2.imgscloud.com/file/8218/8218_055.jpg", "http://hahost2.imgscloud.com/file/8218/8218_056.jpg", "http://hahost2.imgscloud.com/file/8218/8218_057.jpg", "http://hahost2.imgscloud.com/file/8218/8218_058.jpg", "http://hahost2.imgscloud.com/file/8218/8218_059.jpg", "http://hahost2.imgscloud.com/file/8218/8218_060.jpg", "http://hahost2.imgscloud.com/file/8218/8218_061.jpg", "http://hahost2.imgscloud.com/file/8218/8218_062.jpg", "http://hahost2.imgscloud.com/file/8218/8218_063.jpg", "http://hahost2.imgscloud.com/file/8218/8218_064.jpg", "http://hahost2.imgscloud.com/file/8218/8218_065.jpg", "http://hahost2.imgscloud.com/file/8218/8218_066.jpg", "http://hahost2.imgscloud.com/file/8218/8218_067.jpg", "http://hahost2.imgscloud.com/file/8218/8218_068.jpg", "http://hahost2.imgscloud.com/file/8218/8218_069.jpg", "http://hahost2.imgscloud.com/file/8218/8218_070.jpg", "http://hahost2.imgscloud.com/file/8218/8218_071.jpg", "http://hahost2.imgscloud.com/file/8218/8218_072.jpg", "http://hahost2.imgscloud.com/file/8218/8218_073.jpg", "http://hahost2.imgscloud.com/file/8218/8218_074.jpg", "http://hahost2.imgscloud.com/file/8218/8218_075.jpg", "http://hahost2.imgscloud.com/file/8218/8218_076.jpg", "http://hahost2.imgscloud.com/file/8218/8218_077.jpg", "http://hahost2.imgscloud.com/file/8218/8218_078.jpg", "http://hahost2.imgscloud.com/file/8218/8218_079.jpg", "http://hahost2.imgscloud.com/file/8218/8218_080.jpg", "http://hahost2.imgscloud.com/file/8218/8218_081.jpg", "http://hahost2.imgscloud.com/file/8218/8218_082.jpg", "http://hahost2.imgscloud.com/file/8218/8218_083.jpg", "http://hahost2.imgscloud.com/file/8218/8218_084.jpg", "http://hahost2.imgscloud.com/file/8218/8218_085.jpg", "http://hahost2.imgscloud.com/file/8218/8218_086.jpg", "http://hahost2.imgscloud.com/file/8218/8218_087.jpg", "http://hahost2.imgscloud.com/file/8218/8218_088.jpg", "http://hahost2.imgscloud.com/file/8218/8218_089.jpg", "http://hahost2.imgscloud.com/file/8218/8218_090.jpg", "http://hahost2.imgscloud.com/file/8218/8218_091.jpg", "http://hahost2.imgscloud.com/file/8218/8218_092.jpg", "http://hahost2.imgscloud.com/file/8218/8218_093.jpg", "http://hahost2.imgscloud.com/file/8218/8218_094.jpg", "http://hahost2.imgscloud.com/file/8218/8218_095.jpg", "http://hahost2.imgscloud.com/file/8218/8218_096.jpg", "http://hahost2.imgscloud.com/file/8218/8218_097.jpg", "http://hahost2.imgscloud.com/file/8218/8218_098.jpg", "http://hahost2.imgscloud.com/file/8218/8218_099.jpg", "http://hahost2.imgscloud.com/file/8218/8218_100.jpg", "http://hahost2.imgscloud.com/file/8218/8218_101.jpg", "http://hahost2.imgscloud.com/file/8218/8218_102.jpg", "http://hahost2.imgscloud.com/file/8218/8218_103.jpg", "http://hahost2.imgscloud.com/file/8218/8218_104.jpg", "http://hahost2.imgscloud.com/file/8218/8218_105.jpg", "http://hahost2.imgscloud.com/file/8218/8218_106.jpg", "http://hahost2.imgscloud.com/file/8218/8218_107.jpg", "http://hahost2.imgscloud.com/file/8218/8218_108.jpg", "http://hahost2.imgscloud.com/file/8218/8218_109.jpg", "http://hahost2.imgscloud.com/file/8218/8218_110.jpg", "http://hahost2.imgscloud.com/file/8218/8218_111.jpg", "http://hahost2.imgscloud.com/file/8218/8218_112.jpg", "http://hahost2.imgscloud.com/file/8218/8218_113.jpg", "http://hahost2.imgscloud.com/file/8218/8218_114.jpg", "http://hahost2.imgscloud.com/file/8218/8218_115.jpg", "http://hahost2.imgscloud.com/file/8218/8218_116.jpg", "http://hahost2.imgscloud.com/file/8218/8218_117.jpg", "http://hahost2.imgscloud.com/file/8218/8218_118.jpg", "http://hahost2.imgscloud.com/file/8218/8218_119.jpg", "http://hahost2.imgscloud.com/file/8218/8218_120.jpg", "http://hahost2.imgscloud.com/file/8218/8218_121.jpg", "http://hahost2.imgscloud.com/file/8218/8218_122.jpg", "http://hahost2.imgscloud.com/file/8218/8218_123.jpg", "http://hahost2.imgscloud.com/file/8218/8218_124.jpg", "http://hahost2.imgscloud.com/file/8218/8218_125.jpg", "http://hahost2.imgscloud.com/file/8218/8218_126.jpg", "http://hahost2.imgscloud.com/file/8218/8218_127.jpg", "http://hahost2.imgscloud.com/file/8218/8218_128.jpg", "http://hahost2.imgscloud.com/file/8218/8218_129.jpg", "http://hahost2.imgscloud.com/file/8218/8218_130.jpg", "http://hahost2.imgscloud.com/file/8218/8218_131.jpg", "http://hahost2.imgscloud.com/file/8218/8218_132.jpg", "http://hahost2.imgscloud.com/file/8218/8218_133.jpg", "http://hahost2.imgscloud.com/file/8218/8218_134.jpg", "http://hahost2.imgscloud.com/file/8218/8218_135.jpg", "http://hahost2.imgscloud.com/file/8218/8218_136.jpg", "http://hahost2.imgscloud.com/file/8218/8218_137.jpg", "http://hahost2.imgscloud.com/file/8218/8218_138.jpg", "http://hahost2.imgscloud.com/file/8218/8218_139.jpg", "http://hahost2.imgscloud.com/file/8218/8218_140.jpg", "http://hahost2.imgscloud.com/file/8218/8218_141.jpg", "http://hahost2.imgscloud.com/file/8218/8218_142.jpg", "http://hahost2.imgscloud.com/file/8218/8218_143.jpg", "http://hahost2.imgscloud.com/file/8218/8218_144.jpg", "http://hahost2.imgscloud.com/file/8218/8218_145.jpg", "http://hahost2.imgscloud.com/file/8218/8218_146.jpg", "http://hahost2.imgscloud.com/file/8218/8218_147.jpg", "http://hahost2.imgscloud.com/file/8218/8218_148.jpg", "http://hahost2.imgscloud.com/file/8218/8218_149.jpg", "http://hahost2.imgscloud.com/file/8218/8218_150.jpg", "http://hahost2.imgscloud.com/file/8218/8218_151.jpg", "http://hahost2.imgscloud.com/file/8218/8218_152.jpg", "http://hahost2.imgscloud.com/file/8218/8218_153.jpg", "http://hahost2.imgscloud.com/file/8218/8218_154.jpg", "http://hahost2.imgscloud.com/file/8218/8218_155.jpg", "http://hahost2.imgscloud.com/file/8218/8218_156.jpg", "http://hahost2.imgscloud.com/file/8218/8218_157.jpg", "http://hahost2.imgscloud.com/file/8218/8218_158.jpg", "http://hahost2.imgscloud.com/file/8218/8218_159.jpg", "http://hahost2.imgscloud.com/file/8218/8218_160.jpg", "http://hahost2.imgscloud.com/file/8218/8218_161.jpg", "http://hahost2.imgscloud.com/file/8218/8218_162.jpg", "http://hahost2.imgscloud.com/file/8218/8218_163.jpg", "http://hahost2.imgscloud.com/file/8218/8218_164.jpg", "http://hahost2.imgscloud.com/file/8218/8218_165.jpg", "http://hahost2.imgscloud.com/file/8218/8218_166.jpg", "http://hahost2.imgscloud.com/file/8218/8218_167.jpg", "http://hahost2.imgscloud.com/file/8218/8218_168.jpg", "http://hahost2.imgscloud.com/file/8218/8218_169.jpg", "http://hahost2.imgscloud.com/file/8218/8218_170.jpg", "http://hahost2.imgscloud.com/file/8218/8218_171.jpg", "http://hahost2.imgscloud.com/file/8218/8218_172.jpg", "http://hahost2.imgscloud.com/file/8218/8218_173.jpg", "http://hahost2.imgscloud.com/file/8218/8218_174.jpg", "http://hahost2.imgscloud.com/file/8218/8218_175.jpg", "http://hahost2.imgscloud.com/file/8218/8218_176.jpg", "http://hahost2.imgscloud.com/file/8218/8218_177.jpg", "http://hahost2.imgscloud.com/file/8218/8218_178.jpg", "http://hahost2.imgscloud.com/file/8218/8218_179.jpg", "http://hahost2.imgscloud.com/file/8218/8218_180.jpg", "http://hahost2.imgscloud.com/file/8218/8218_181.jpg", "http://hahost2.imgscloud.com/file/8218/8218_182.jpg", "http://hahost2.imgscloud.com/file/8218/8218_183.jpg", "http://hahost2.imgscloud.com/file/8218/8218_184.jpg", "http://hahost2.imgscloud.com/file/8218/8218_185.jpg", "http://hahost2.imgscloud.com/file/8218/8218_186.jpg", "http://hahost2.imgscloud.com/file/8218/8218_187.jpg", "http://hahost2.imgscloud.com/file/8218/8218_188.jpg", "http://hahost2.imgscloud.com/file/8218/8218_189.jpg", "http://hahost2.imgscloud.com/file/8218/8218_190.jpg", "http://hahost2.imgscloud.com/file/8218/8218_191.jpg", "http://hahost2.imgscloud.com/file/8218/8218_192.jpg", "http://hahost2.imgscloud.com/file/8218/8218_193.jpg", "http://hahost2.imgscloud.com/file/8218/8218_194.jpg", "http://hahost2.imgscloud.com/file/8218/8218_195.jpg", "http://hahost2.imgscloud.com/file/8218/8218_196.jpg", "http://hahost2.imgscloud.com/file/8218/8218_197.jpg", "http://hahost2.imgscloud.com/file/8218/8218_198.jpg", "http://hahost2.imgscloud.com/file/8218/8218_199.jpg", "http://hahost2.imgscloud.com/file/8218/8218_200.jpg", "http://hahost2.imgscloud.com/file/8218/8218_201.jpg", "http://hahost2.imgscloud.com/file/8218/8218_202.jpg", "http://hahost2.imgscloud.com/file/8218/8218_203.jpg", "http://hahost2.imgscloud.com/file/8218/8218_204.jpg", "http://hahost2.imgscloud.com/file/8218/8218_205.jpg"]}, {"category": 1, "name": "[\u5009\u79d1\u907c, \u5c0f\u6797\u62d3\u5df1]\u80f8\u61f7\u5927\u5fd7 \u7b2c4\u5dfb_\u3044\u3064\u304b\u52dd\u3061\u7d44! \u7b2c4\u5dfb", "source_link": "http://18h.mm-cg.com/18H_5539.html", "created_at": "2017-11-07T16:28:40.867Z", "cover": "http://hahost2.imgscloud.com/file/8217/8217_001.jpg", "images": ["http://hahost2.imgscloud.com/file/8217/8217_001.jpg", "http://hahost2.imgscloud.com/file/8217/8217_002.jpg", "http://hahost2.imgscloud.com/file/8217/8217_003.jpg", "http://hahost2.imgscloud.com/file/8217/8217_004.jpg", "http://hahost2.imgscloud.com/file/8217/8217_005.jpg", "http://hahost2.imgscloud.com/file/8217/8217_006.jpg", "http://hahost2.imgscloud.com/file/8217/8217_007.jpg", "http://hahost2.imgscloud.com/file/8217/8217_008.jpg", "http://hahost2.imgscloud.com/file/8217/8217_009.jpg", "http://hahost2.imgscloud.com/file/8217/8217_010.jpg", "http://hahost2.imgscloud.com/file/8217/8217_011.jpg", "http://hahost2.imgscloud.com/file/8217/8217_012.jpg", "http://hahost2.imgscloud.com/file/8217/8217_013.jpg", "http://hahost2.imgscloud.com/file/8217/8217_014.jpg", "http://hahost2.imgscloud.com/file/8217/8217_015.jpg", "http://hahost2.imgscloud.com/file/8217/8217_016.jpg", "http://hahost2.imgscloud.com/file/8217/8217_017.jpg", "http://hahost2.imgscloud.com/file/8217/8217_018.jpg", "http://hahost2.imgscloud.com/file/8217/8217_019.jpg", "http://hahost2.imgscloud.com/file/8217/8217_020.jpg", "http://hahost2.imgscloud.com/file/8217/8217_021.jpg", "http://hahost2.imgscloud.com/file/8217/8217_022.jpg", "http://hahost2.imgscloud.com/file/8217/8217_023.jpg", "http://hahost2.imgscloud.com/file/8217/8217_024.jpg", "http://hahost2.imgscloud.com/file/8217/8217_025.jpg", "http://hahost2.imgscloud.com/file/8217/8217_026.jpg", "http://hahost2.imgscloud.com/file/8217/8217_027.jpg", "http://hahost2.imgscloud.com/file/8217/8217_028.jpg", "http://hahost2.imgscloud.com/file/8217/8217_029.jpg", "http://hahost2.imgscloud.com/file/8217/8217_030.jpg", "http://hahost2.imgscloud.com/file/8217/8217_031.jpg", "http://hahost2.imgscloud.com/file/8217/8217_032.jpg", "http://hahost2.imgscloud.com/file/8217/8217_033.jpg", "http://hahost2.imgscloud.com/file/8217/8217_034.jpg", "http://hahost2.imgscloud.com/file/8217/8217_035.jpg", "http://hahost2.imgscloud.com/file/8217/8217_036.jpg", "http://hahost2.imgscloud.com/file/8217/8217_037.jpg", "http://hahost2.imgscloud.com/file/8217/8217_038.jpg", "http://hahost2.imgscloud.com/file/8217/8217_039.jpg", "http://hahost2.imgscloud.com/file/8217/8217_040.jpg", "http://hahost2.imgscloud.com/file/8217/8217_041.jpg", "http://hahost2.imgscloud.com/file/8217/8217_042.jpg", "http://hahost2.imgscloud.com/file/8217/8217_043.jpg", "http://hahost2.imgscloud.com/file/8217/8217_044.jpg", "http://hahost2.imgscloud.com/file/8217/8217_045.jpg", "http://hahost2.imgscloud.com/file/8217/8217_046.jpg", "http://hahost2.imgscloud.com/file/8217/8217_047.jpg", "http://hahost2.imgscloud.com/file/8217/8217_048.jpg", "http://hahost2.imgscloud.com/file/8217/8217_049.jpg", "http://hahost2.imgscloud.com/file/8217/8217_050.jpg", "http://hahost2.imgscloud.com/file/8217/8217_051.jpg", "http://hahost2.imgscloud.com/file/8217/8217_052.jpg", "http://hahost2.imgscloud.com/file/8217/8217_053.jpg", "http://hahost2.imgscloud.com/file/8217/8217_054.jpg", "http://hahost2.imgscloud.com/file/8217/8217_055.jpg", "http://hahost2.imgscloud.com/file/8217/8217_056.jpg", "http://hahost2.imgscloud.com/file/8217/8217_057.jpg", "http://hahost2.imgscloud.com/file/8217/8217_058.jpg", "http://hahost2.imgscloud.com/file/8217/8217_059.jpg", "http://hahost2.imgscloud.com/file/8217/8217_060.jpg", "http://hahost2.imgscloud.com/file/8217/8217_061.jpg", "http://hahost2.imgscloud.com/file/8217/8217_062.jpg", "http://hahost2.imgscloud.com/file/8217/8217_063.jpg", "http://hahost2.imgscloud.com/file/8217/8217_064.jpg", "http://hahost2.imgscloud.com/file/8217/8217_065.jpg", "http://hahost2.imgscloud.com/file/8217/8217_066.jpg", "http://hahost2.imgscloud.com/file/8217/8217_067.jpg", "http://hahost2.imgscloud.com/file/8217/8217_068.jpg", "http://hahost2.imgscloud.com/file/8217/8217_069.jpg", "http://hahost2.imgscloud.com/file/8217/8217_070.jpg", "http://hahost2.imgscloud.com/file/8217/8217_071.jpg", "http://hahost2.imgscloud.com/file/8217/8217_072.jpg", "http://hahost2.imgscloud.com/file/8217/8217_073.jpg", "http://hahost2.imgscloud.com/file/8217/8217_074.jpg", "http://hahost2.imgscloud.com/file/8217/8217_075.jpg", "http://hahost2.imgscloud.com/file/8217/8217_076.jpg", "http://hahost2.imgscloud.com/file/8217/8217_077.jpg", "http://hahost2.imgscloud.com/file/8217/8217_078.jpg", "http://hahost2.imgscloud.com/file/8217/8217_079.jpg", "http://hahost2.imgscloud.com/file/8217/8217_080.jpg", "http://hahost2.imgscloud.com/file/8217/8217_081.jpg", "http://hahost2.imgscloud.com/file/8217/8217_082.jpg", "http://hahost2.imgscloud.com/file/8217/8217_083.jpg", "http://hahost2.imgscloud.com/file/8217/8217_084.jpg", "http://hahost2.imgscloud.com/file/8217/8217_085.jpg", "http://hahost2.imgscloud.com/file/8217/8217_086.jpg", "http://hahost2.imgscloud.com/file/8217/8217_087.jpg", "http://hahost2.imgscloud.com/file/8217/8217_088.jpg", "http://hahost2.imgscloud.com/file/8217/8217_089.jpg", "http://hahost2.imgscloud.com/file/8217/8217_090.jpg", "http://hahost2.imgscloud.com/file/8217/8217_091.jpg", "http://hahost2.imgscloud.com/file/8217/8217_092.jpg", "http://hahost2.imgscloud.com/file/8217/8217_093.jpg", "http://hahost2.imgscloud.com/file/8217/8217_094.jpg", "http://hahost2.imgscloud.com/file/8217/8217_095.jpg", "http://hahost2.imgscloud.com/file/8217/8217_096.jpg", "http://hahost2.imgscloud.com/file/8217/8217_097.jpg", "http://hahost2.imgscloud.com/file/8217/8217_098.jpg", "http://hahost2.imgscloud.com/file/8217/8217_099.jpg", "http://hahost2.imgscloud.com/file/8217/8217_100.jpg", "http://hahost2.imgscloud.com/file/8217/8217_101.jpg", "http://hahost2.imgscloud.com/file/8217/8217_102.jpg", "http://hahost2.imgscloud.com/file/8217/8217_103.jpg", "http://hahost2.imgscloud.com/file/8217/8217_104.jpg", "http://hahost2.imgscloud.com/file/8217/8217_105.jpg"]}]