[{"category": 0, "url": "http://video.520cc.cc/player3G.php?id=GY2Y8GDS09DMFRoYVdUejdDOE56YzlZdGYwd1NOaHBKN3ZicUtLaWx6bEdlTzI1Zz0=", "created_at": "2017-11-07T14:20:37.631Z", "cover": "http://att.520cc.me/data/attachment/forum/201708/23/202903m8mu88uh37l891uu.jpg", "name": "PGD-952 \u7fa9\u59ca\u4e2d\u51fa\u8a98\u60d1 \u9ebb\u91cc\u68a8\u590f"}, {"category": 0, "url": "http://video.520cc.cc/player3G.php?id=u5dw3GDS09DMFRoYVdUejVOaXFFcjFEd1VBV0tvS3Vtc3hQT2ZTNENibzZjeW5QND0=", "created_at": "2017-11-07T14:20:34.423Z", "cover": "http://att.520cc.me/data/attachment/forum/201708/23/063908r9dmpvq9vvov9l2q.jpg", "name": "ATID-284 \u9019\u9ebc\u7684\u6fd5\uff0c\u7121\u6cd5\u5c0d\u8001\u516c\u8aaa \u677e\u4e0b\u7d17\u69ae\u5b50"}, {"category": 0, "url": "http://video.520cc.cc/player3G.php?id=PcF3uGDS09DMFRoYVdUejRMZXowWUxVRXhRck1pVUtsZmE0WVdLVGYvNWVrODhzMD0=", "created_at": "2017-11-07T14:20:33.104Z", "cover": "http://att.520cc.me/data/attachment/forum/201708/23/063910klfx04eqfercex00.jpg", "name": "HD LXVS-029 LuxuTV\u00d7PRESTIGE \u5ca1\u5d0e\u590f\u76ee[\u6709\u78bc\u9ad8\u6e05\u4e2d\u6587\u5b57\u5e55]"}, {"category": 0, "url": "http://video.520cc.cc/player3G.php?id=g6r5qGDS09DMFRoYVdUejU1WlZVbXZSOFVQZXhBVm41YmVCc1Y4Snd2SThvQUZJdz0=", "created_at": "2017-11-07T14:20:31.249Z", "cover": "http://att.520cc.me/data/attachment/forum/201708/23/065909p6w657uop51yr62d.jpg", "name": "KKJ-058 \u8a8d\u771f\u628a\u59b9 \u4eba\u59bb\u7bc7 37 \u642d\u8a15\u2192\u5916\u5e36\u2192\u5e79\u7832\u5077\u62cd\u2192\u64c5\u81eaPO\u7db2"}, {"category": 0, "url": "http://video.520cc.cc/player3G.php?id=ai5S5GDS09DMFRoYVdUejY0cVROb2ZwVXVEaXpvNzJsRWF6VC92UUFoWkNwUkRqRT0=", "created_at": "2017-11-07T14:20:30.009Z", "cover": "http://att.520cc.me/data/attachment/forum/201708/23/154941wa61zbnx7xbjnhhx.jpg", "name": "EYAN-091 E-BODY \u53f2\u4e0a\u6700\u5f37NO.1\u5b8c\u7f8e\u66f2\u7dda \u4eba\u59bb\u51fa\u9053 \u4e26\u6a39\u5149"}, {"category": 0, "url": "http://video.520cc.cc/player3G.php?id=cL7qzGDS09DMFRoYVdUejVOSU1wd2pFSEFhbGM3QktiOXd3WWVNcGtaVHhwKzQ1ND0=", "created_at": "2017-11-07T14:20:28.691Z", "cover": "http://att.520cc.me/data/attachment/forum/201708/23/075906tziidd1cfa7eswu1.jpg", "name": "[HBAD-322] \u662d\u548c\u5973\u7684\u60b2\u6b4c\u300e\u5728\u907f\u96e3\u7684\u9109\u4e0b\u6dea\u70ba\u51fa\u5f81\u5175\u58eb\u5011\u7684\u6170\u5b89\u5a66\u7684\u9ad8\u50b2\u8cb4\u5a66\u4eba1945\u300f \u661f\u91ce\u6731\u8389"}, {"category": 0, "url": "http://video.520cc.cc/player3G.php?id=c0135GDS09DMFRoYVdUejRxNmFFNWdOdUx0NmR5WktMelBTL0l3bmpOb2pVS2JNWT0=", "created_at": "2017-11-07T14:20:27.350Z", "cover": "http://att.520cc.me/data/attachment/forum/201708/23/181822qhdmjecjeeajjyh6.jpg", "name": "[DIC-023] \u6821\u5712\u9078\u7f8e\u51a0\u8ecd 8\u982d\u8eab\u7e96\u7d30\u7f8e\u5973\uff01\u73fe\u5728\u55ae\u7d14\u53ef\u611b\u5973\u5927\u751f\u62cdAV \u5409\u7530\u512a\u5e0c"}, {"category": 0, "url": "http://video.520cc.cc/player3G.php?id=laTcdGDS09DMFRoYVdUejVZZGxPb3hPM0lGT1haaThucHloQW44VGpGcjE4cm9Tcz0=", "created_at": "2017-11-07T14:20:26.193Z", "cover": "http://att.520cc.me/data/attachment/forum/201708/23/075949w09yu0u0yzutzgyc.jpg", "name": "EYAN-090 \u96e3\u6ce2\u7684\u6bcd\u4e73\u5c11\u5a66\u3001\u6e34\u6c42\u60c5\u71b1\u4e0a\u4eacAV\u651d\u5f71\uff01\u6bcd\u4e73\u98db\u6ffa\u6fc0\u70c8\u9ad8\u6f6e3\u6027\u4ea4 \u5b8c\u5168\u7121\u526a\u8f2fSP \u7d50\u6708\u606d\u5b50"}, {"category": 0, "url": "http://video.520cc.cc/player3G.php?id=MAWlgGDS09DMFRoYVdUejdBSjdXQjFHNVIxM3p5S0hWSlprc0ptSStZdjUvekhycz0=", "created_at": "2017-11-07T14:20:24.757Z", "cover": "http://att.520cc.me/data/attachment/forum/201708/23/080907vrrz5rl49odi4i99.jpg", "name": "[UGUG-105] \u5abd\u5abd\u7121\u6cd5\u5fcd\u53d7\u7d42\u65bc\u5931\u7981\u3002\u7531\u539f\u672c\u7684\u5bb3\u7f9e\u8b8a\u6210\u767c\u60c5..."}, {"category": 0, "url": "http://video.520cc.cc/player3G.php?id=kW64VGDS09DMFRoYVdUejdUeGdtY2FkVXUzSkVCVE91S2ZxY2JwbTJPS2lnT3ZXVT0=", "created_at": "2017-11-07T14:20:22.399Z", "cover": "http://att.520cc.me/data/attachment/forum/201708/23/081904u6964czd6xnm1ym9.jpg", "name": "HD IPZ-758 \u88ab\u4e0a\u4e86\u7684\u65b0\u4eba\u7f8e\u5973RQ \u7121\u6cd5\u62d2\u7d55\u88ab\u8feb\u966a\u7761\u7684\u7f8e\u88f8\u9ad4\u3002\u3002\u5e0c\u5d0e\u6f54\u897f\u5361[\u6709\u78bc\u9ad8\u6e05\u4e2d\u6587\u5b57\u5e55]"}]